toml_bench/__init__.py
toml_bench/__main__.py
toml_bench/api.py
toml_bench/cases/__init__.py
toml_bench/cases/compliance.py
toml_bench/cases/hetero_array.py
toml_bench/cases/keys_order.py
toml_bench/cases/speed.py
toml_bench/cases/unicode.py
toml_bench/cases/value_none.py
toml_bench/cases/version.py
toml_bench/sets.py
toml_bench/suite.py
toml_bench/utils.py
toml_bench-0.3.1.dist-info/LICENSE
toml_bench-0.3.1.dist-info/METADATA
toml_bench-0.3.1.dist-info/WHEEL
toml_bench-0.3.1.dist-info/entry_points.txt
toml_bench-0.3.1.dist-info/RECORD
