Metadata-Version: 2.1
Name: toml-bench
Version: 0.3.1
Summary: Benchmarking for python toml libraries
License: MIT
Author: pwwang
Author-email: pwwang@pwwang.com
Requires-Python: >=3.9,<4.0
Classifier: License :: OSI Approved :: MIT License
Classifier: Programming Language :: Python :: 3
Classifier: Programming Language :: Python :: 3.9
Classifier: Programming Language :: Python :: 3.10
Classifier: Programming Language :: Python :: 3.11
Requires-Dist: benchwork (>=0.0.2,<0.0.3)
Requires-Dist: importlib-metadata (>=5.0.0,<6.0.0)
Requires-Dist: pyparam (>=0.5,<0.6)
Requires-Dist: python-dateutil (>=2.8.2,<3.0.0)
Requires-Dist: pytomlpp (>=1.0.13,<2.0.0) ; python_version < "3.11"
Requires-Dist: qtoml (>=0.3.1,<0.4.0)
Requires-Dist: regex (>=2022.10.31,<2023.0.0)
Requires-Dist: rtoml (>=0.9.0,<0.10.0)
Requires-Dist: toml (>=0.10.2,<0.11.0)
Requires-Dist: tomli (>=2.0.1,<3.0.0)
Requires-Dist: tomli-w (>=1.0.0,<2.0.0)
Requires-Dist: tomlkit (>=0.11.8,<0.12.0)
